boot/__init__.py
boot/cli.py
boot/core/__init__.py
boot/core/file_packager.py
boot/core/plugin_installer.py
boot/core/plugin_manager.py
boot/core/prompt_engine.py
boot/core/spec_loader.py
boot/core/writer.py
boot/errors.py
boot/generated/__init__.py
boot/generated/plugin_pb2.py
boot/generated/plugin_pb2_grpc.py
boot/llm/__init__.py
boot/llm/factory.py
boot/llm/providers/__init__.py
boot/llm/providers/gemini.py
boot/llm/providers/openai.py
boot/llm/service.py
boot/llm/types.py
boot/models/__init__.py
boot/models/config.py
boot/models/spec.py
boot/parsers/__init__.py
boot/parsers/factory.py
boot/parsers/languages/__init__.py
boot/parsers/languages/python.py
boot/parsers/languages/rust.py
boot/parsers/types.py
boot/py.typed
boot/services.py
boot/ui/__init__.py
boot/ui/console.py
boot/ui/help.py
boot/utils/__init__.py
boot/utils/constants.py
boot/utils/helpers.py
boot_code-0.1.4.dist-info/LICENSE.md
boot_code-0.1.4.dist-info/METADATA
boot_code-0.1.4.dist-info/WHEEL
boot_code-0.1.4.dist-info/entry_points.txt
boot_code-0.1.4.dist-info/RECORD
