Metadata-Version: 2.3
Name: boot-code
Version: 0.1.4
Summary: Spec-driven, build passing code.
Author: Bordumb
Author-email: bordumbb@gmail.com
Requires-Python: >=3.11
Classifier: Programming Language :: Python :: 3
Classifier: Programming Language :: Python :: 3.11
Classifier: Programming Language :: Python :: 3.12
Classifier: Programming Language :: Python :: 3.13
Requires-Dist: grpcio (>=1.74.0,<2.0.0)
Requires-Dist: httpx (>=0.27.0)
Requires-Dist: jinja2 (>=3.1.0)
Requires-Dist: protobuf (==6.31.1)
Requires-Dist: pydantic (>=2.7.0)
Requires-Dist: pydantic-settings (>=2.2.0)
Requires-Dist: pyfiglet (>=1.0.2)
Requires-Dist: python-dotenv (>=1.0.0)
Requires-Dist: pyyaml (>=6.0)
Requires-Dist: rich (==13.3.5)
Requires-Dist: typer[all] (==0.9.0)
